kezmenu3/__init__.py
kezmenu3/kezmenu.py
kezmenu3/kezmenu_effects.py
kezmenu3-0.3.6.dist-info/top_level.txt
kezmenu3-0.3.6.dist-info/METADATA
kezmenu3-0.3.6.dist-info/DESCRIPTION.rst
kezmenu3-0.3.6.dist-info/metadata.json
kezmenu3-0.3.6.dist-info/WHEEL
kezmenu3-0.3.6.dist-info/RECORD
