Metadata-Version: 2.0
Name: kezmenu3
Version: 0.3.6
Summary: KezMenu3 is a KezMenu fork for Python2 and 3.
Home-page: https://github.com/a-tal/kezmenu3
Author: Adam Talsma
Author-email: adam@talsma.ca
License: GPL
Download-URL: https://github.com/a-tal/kezmenu3
Platform: UNKNOWN
Classifier: Programming Language :: Python
